{
    "1": {
        "name": "Сыр",
        "manufacturer": "Звездочка"
    },
    "2": {
        "name": "Молоко",
        "manufacturer": "Звезда"
    },
    "3": {
        "name": "Икра",
        "manufacturer": "Ромашка"
    },
    "4": {
        "name": "Хлеб чёрный",
        "manufacturer": "Хлебокомбинат №4"
    },
    "5": {
        "name": "Хлеб белый",
        "manufacturer": "Хлебокомбинат №4"
    },
    "Творог": {
        "name": "Творог",
        "manufacturer": "Молокозавод"
    },
    "123": {
        "name": "мочалка",
        "manufacturer": "сельхозмаг"
    },
    "1234": {
        "name": "сырок",
        "manufacturer": "я"
    }
}